klupywpredictorx/__init__.py
klupywpredictorx/crash.py
klupywpredictorx/mines.py
klupywpredictorx/towers.py
klupywpredictorx-3.0.2.dist-info/LICENSE
klupywpredictorx-3.0.2.dist-info/METADATA
klupywpredictorx-3.0.2.dist-info/WHEEL
klupywpredictorx-3.0.2.dist-info/top_level.txt
klupywpredictorx-3.0.2.dist-info/RECORD
