Metadata-Version: 2.1
Name: klupywpredictorx
Version: 3.0.2
Summary: A package that predicts bloxflip games by Maska
Author: maska
Author-email: mask121575@gmail.com
Keywords: python,bloxflip,klupywpredictorx,predictor
Classifier: Development Status :: 1 - Planning
Classifier: Intended Audience :: Developers
Classifier: Programming Language :: Python :: 3
Classifier: Operating System :: Unix
Classifier: Operating System :: MacOS :: MacOS X
Classifier: Operating System :: Microsoft :: Windows
License-File: LICENSE
Requires-Dist: cloudscraper
